FPGA_implementation/nbit_counter.sv
module nbit_counter #(
    parameter n = 4
  )(
    input logic trig,
    output logic [n-1 : 0] count = 0
  );

  // Increment by one at the positive edge of the trig signal
  always @(posedge trig)
  begin
    count <= count + 1;
  end

endmodule

FPGA_implementation/tb_nbit_counter.sv
module nbit_counter_tb;

  localparam  n = 4;

  reg trig = 0;
  wire logic [n : 0] count;

  nbit_counter # (
    .n(n)
  )
  nbit_counter_inst (
    .trig(trig),
    .count(count)
  );

  always #5 trig = !trig;

  initial begin
    $dumpfile("waveform.vcd");
    $dumpvars(0, nbit_counter_tb);
    #200 $finish;
  end

endmodule

FPGA_implementation/waveform.vcd
$date
	Sun Jan 11 23:10:04 2026
$end
$version
	Icarus Verilog
$end
$timescale
	1s
$end
$scope module nbit_counter_tb $end
$var wire 5 ! count [4:0] $end
$var parameter 32 " n $end
$var reg 1 # trig $end
$scope module nbit_counter_inst $end
$var wire 1 # trig $end
$var parameter 32 $ n $end
$var reg 5 % count [4:0] $end
$upscope $end
$upscope $end
$enddefinitions $end
$comment Show the parameter values. $end
$dumpall
b100 $
b100 "
$end
#0
$dumpvars
b0 %
0#
b0 !
$end
#5
b1 !
b1 %
1#
#10
0#
#15
b10 !
b10 %
1#
#20
0#
#25
b11 !
b11 %
1#
#30
0#
#35
b100 !
b100 %
1#
#40
0#
#45
b101 !
b101 %
1#
#50
0#
#55
b110 !
b110 %
1#
#60
0#
#65
b111 !
b111 %
1#
#70
0#
#75
b1000 !
b1000 %
1#
#80
0#
#85
b1001 !
b1001 %
1#
#90
0#
#95
b1010 !
b1010 %
1#
#100
0#
#105
b1011 !
b1011 %
1#
#110
0#
#115
b1100 !
b1100 %
1#
#120
0#
#125
b1101 !
b1101 %
1#
#130
0#
#135
b1110 !
b1110 %
1#
#140
0#
#145
b1111 !
b1111 %
1#
#150
0#
#155
b10000 !
b10000 %
1#
#160
0#
#165
b10001 !
b10001 %
1#
#170
0#
#175
b10010 !
b10010 %
1#
#180
0#
#185
b10011 !
b10011 %
1#
#190
0#
#195
b10100 !
b10100 %
1#
#200
0#
